{"py/object": "rasa.core.featurizers.tracker_featurizers.MaxHistoryTrackerFeaturizer", "state_featurizer": {"py/object": "rasa.core.featurizers.single_state_featurizer.SingleStateFeaturizer", "_default_feature_states": {"intent": {"back": 0, "choose_discipline": 1, "choose_topic": 2, "definition": 3, "greet": 4, "nlu_fallback": 5, "out_of_scope": 6, "restart": 7, "session_start": 8, "user_responds_to_topic": 9}, "action_name": {"action_listen": 0, "action_restart": 1, "action_session_start": 2, "action_default_fallback": 3, "action_deactivate_loop": 4, "action_revert_fallback_events": 5, "action_default_ask_affirmation": 6, "action_default_ask_rephrase": 7, "action_two_stage_fallback": 8, "action_unlikely_intent": 9, "action_back": 10, "...": 11, "action_extract_slots": 12, "utter_greet": 13, "utter_please_rephrase": 14, "action_start_decision_tree": 15, "action_save_science_discipline": 16, "action_explore_topic": 17, "action_save_subtopic": 18, "action_reset_subtopic": 19, "action_rag_abstract_explain": 20, "action_rag_5W1H": 21, "action_faq_answering": 22, "action_check_slots": 23, "action_clear_slots": 24, "action_research_question": 25}, "entities": {"has_topic": 0, "reason": 1, "research_question": 2, "science_discipline": 3, "topic": 4}, "slots": {"has_topic_0": 0, "topic_0": 1, "science_discipline_0": 2, "continue_conversation_0": 3, "continue_conversation_1": 4}, "active_loop": {}}, "action_texts": [], "entity_tag_specs": []}, "max_history": 5, "remove_duplicates": true}